setup.cfg
setup.py
PqrUploadModule/__init__.py
PqrUploadModule/actions.py
PqrUploadModule/actions_notes_counterparts.py
PqrUploadModule/attachment_counterparts.py
PqrUploadModule/attachments.py
PqrUploadModule/authorizations.py
PqrUploadModule/contacts.py
PqrUploadModule/contacts_update.py
PqrUploadModule/hard_coded_relations.py
PqrUploadModule/incidents.py
PqrUploadModule/notes.py
PqrUploadModule/scan.py
PqrUploadModule/scanning.py
PqrUploadModule/start_settings.py
PqrUploadModule/ticket_incidents_counterparts.py
PqrUploadModule/tickets.py
PqrUploadModule/tickets_incidents_counterparts.py
PqrUploadModule.egg-info/PKG-INFO
PqrUploadModule.egg-info/SOURCES.txt
PqrUploadModule.egg-info/dependency_links.txt
PqrUploadModule.egg-info/requires.txt
PqrUploadModule.egg-info/top_level.txt