Metadata-Version: 1.1
Name: PqrUploadModule
Version: 0.0.12
Summary: Connection AT-TD
Home-page: https://github.com/petronije2002/PqrUpload/
Author: ppp
Author-email: petronije2002@gmail.com
License: MIT
Download-URL: https://github.com/petronije2002/PqrUpload/archive/0.0.10.tar.gz
Keywords: Autotask,Topdesk,Connection
Platform: UNKNOWN
Classifier: Development Status :: 3 - Alpha
Classifier: Intended Audience :: Developers
Classifier: Topic :: Software Development :: Build Tools
Classifier: License :: OSI Approved :: MIT License
Classifier: Programming Language :: Python :: 3
Classifier: Programming Language :: Python :: 3.4
Classifier: Programming Language :: Python :: 3.5
Classifier: Programming Language :: Python :: 3.6
